<?xml version="1.0"?>
<api>
  <query>
    <pages>
      <page pageid="143204" ns="0" title="ポール・アレン">
        <langlinks>
          <ll lang="ar" xml:space="preserve">بول ألين</ll>
          <ll lang="be" xml:space="preserve">Пол Ален</ll>
          <ll lang="bg" xml:space="preserve">Пол Алън</ll>
          <ll lang="bn" xml:space="preserve">পল অ্যালেন</ll>
          <ll lang="br" xml:space="preserve">Paul Allen</ll>
          <ll lang="ca" xml:space="preserve">Paul Allen</ll>
          <ll lang="cs" xml:space="preserve">Paul Allen</ll>
          <ll lang="da" xml:space="preserve">Paul Allen</ll>
          <ll lang="de" xml:space="preserve">Paul Allen</ll>
          <ll lang="el" xml:space="preserve">Πολ Άλεν</ll>
          <ll lang="en" xml:space="preserve">Paul Allen</ll>
          <ll lang="eo" xml:space="preserve">Paul Allen</ll>
          <ll lang="es" xml:space="preserve">Paul Allen</ll>
          <ll lang="et" xml:space="preserve">Paul Allen</ll>
          <ll lang="eu" xml:space="preserve">Paul Allen</ll>
          <ll lang="fa" xml:space="preserve">پل آلن</ll>
          <ll lang="fi" xml:space="preserve">Paul Allen</ll>
          <ll lang="fr" xml:space="preserve">Paul Allen</ll>
          <ll lang="gl" xml:space="preserve">Paul Allen</ll>
          <ll lang="he" xml:space="preserve">פול אלן</ll>
          <ll lang="hi" xml:space="preserve">पॉल एलन</ll>
          <ll lang="id" xml:space="preserve">Paul Allen</ll>
          <ll lang="it" xml:space="preserve">Paul Allen</ll>
          <ll lang="ka" xml:space="preserve">პოლ ალენი</ll>
          <ll lang="ko" xml:space="preserve">폴 앨런</ll>
          <ll lang="lt" xml:space="preserve">Paul Allen</ll>
          <ll lang="lv" xml:space="preserve">Pols Allens</ll>
          <ll lang="ml" xml:space="preserve">പോൾ അല്ലൻ</ll>
          <ll lang="ms" xml:space="preserve">Paul Allen</ll>
          <ll lang="mt" xml:space="preserve">Paul Allen</ll>
          <ll lang="my" xml:space="preserve">ပေါလ် အယ်လန်</ll>
          <ll lang="nl" xml:space="preserve">Paul Allen</ll>
          <ll lang="nn" xml:space="preserve">Paul Allen</ll>
          <ll lang="no" xml:space="preserve">Paul Allen</ll>
          <ll lang="pam" xml:space="preserve">Paul Allen</ll>
          <ll lang="pl" xml:space="preserve">Paul Allen</ll>
          <ll lang="pnb" xml:space="preserve">پال ایلن</ll>
          <ll lang="pt" xml:space="preserve">Paul Allen</ll>
          <ll lang="ro" xml:space="preserve">Paul Allen</ll>
          <ll lang="ru" xml:space="preserve">Аллен, Пол</ll>
          <ll lang="simple" xml:space="preserve">Paul Allen</ll>
          <ll lang="sk" xml:space="preserve">Paul Allen</ll>
          <ll lang="sr" xml:space="preserve">Пол Ален</ll>
          <ll lang="sv" xml:space="preserve">Paul Allen</ll>
          <ll lang="th" xml:space="preserve">พอล อัลเลน</ll>
          <ll lang="tl" xml:space="preserve">Paul Allen</ll>
          <ll lang="tr" xml:space="preserve">Paul Gardner Allen</ll>
          <ll lang="uk" xml:space="preserve">Пол Аллен</ll>
          <ll lang="vi" xml:space="preserve">Paul Allen</ll>
          <ll lang="zh" xml:space="preserve">保罗·艾伦</ll>
        </langlinks>
      </page>
    </pages>
  </query>
</api>